setGPU.py
setup.py
setGPU.egg-info/PKG-INFO
setGPU.egg-info/SOURCES.txt
setGPU.egg-info/dependency_links.txt
setGPU.egg-info/requires.txt
setGPU.egg-info/top_level.txt