Metadata-Version: 1.0
Name: setGPU
Version: 0.0.7
Summary: A small Python library that automatically sets CUDA_VISIBLE_DEVICES to the least-loaded GPU on multi-GPU systems.
Home-page: https://github.com/bamos/setGPU
Author: Brandon Amos
Author-email: bamos@cs.cmu.edu
License: Public Domain
Platform: any
